pdkmaster/io/klayout/__init__.py
pdkmaster/io/klayout/doit.py
pdkmaster/io/klayout/export.py
pdkmaster/io/klayout/geometry.py
pdkmaster/io/klayout/import_.py
pdkmaster/io/klayout/merge_.py
pdkmaster/io/klayout/pcell.py
pdkmaster_io_klayout-0.1.8.dist-info/METADATA
pdkmaster_io_klayout-0.1.8.dist-info/WHEEL
pdkmaster_io_klayout-0.1.8.dist-info/entry_points.txt
pdkmaster_io_klayout-0.1.8.dist-info/licenses/LICENSE.md
pdkmaster_io_klayout-0.1.8.dist-info/RECORD
