Metadata-Version: 2.1
Name: pdkmaster-io-klayout
Version: 0.1.8
Summary: KLayout interoperation for PDKMaster
Author: Chips4Makers contributors
License: GPL-2.0-or-later OR AGPL-3.0-or-later OR CERN-OHL-S-2.0+
Requires-Python: ~=3.8
Requires-Dist: PDKMaster~=0.12.0
Requires-Dist: pdkmaster-io-spice~=0.1.0
Requires-Dist: klayout>=0.28.17.post1
